python_optimization/__init__.py
python_optimization/python_optimization.py
python_optimization-0.0.9.dist-info/METADATA
python_optimization-0.0.9.dist-info/WHEEL
python_optimization-0.0.9.dist-info/top_level.txt
python_optimization-0.0.9.dist-info/RECORD
