Metadata-Version: 2.1
Name: python_optimization
Version: 0.0.9
Summary: python optimization
Author: founder synergy
Author-email: founders.synergy@gmail.com
Keywords: python
Classifier: Development Status :: 1 - Planning
Classifier: Intended Audience :: Developers
Classifier: Programming Language :: Python :: 3
Classifier: Operating System :: Unix
Classifier: Operating System :: MacOS :: MacOS X
Classifier: Operating System :: Microsoft :: Windows
